q5/__init__.py
q5/_version.py
q5/app.py
q5/draw.py
q5/engine.cp310-win_amd64.pyd
q5-0.1.2.dist-info/LICENSE
q5-0.1.2.dist-info/METADATA
q5-0.1.2.dist-info/WHEEL
q5-0.1.2.dist-info/top_level.txt
q5-0.1.2.dist-info/RECORD
